{"createdAt":"2025-07-21T19:31:50.104Z","updatedAt":"2025-07-21T19:33:06.727Z","id":"OQSTU7Q7tjTZe0dt","name":"My workflow","active":false,"isArchived":true,"nodes":[{"parameters":{},"type":"n8n-nodes-base.manualTrigger","typeVersion":1,"position":[0,0],"id":"20994996-12b1-44e0-a6de-5059353b3c7b","name":"When clicking ‘Execute workflow’"},{"parameters":{"resource":"credential","operation":"getSchema","requestOptions":{}},"type":"n8n-nodes-base.n8n","typeVersion":1,"position":[208,0],"id":"011df5a2-9e42-4898-84c0-465394b24e62","name":"Get credential data schema for type","credentials":{"n8nApi":{"id":"b15XlgVoYsImy6AI","name":"n8n account"}}}],"connections":{"When clicking ‘Execute workflow’":{"main":[[{"node":"Get credential data schema for type","type":"main","index":0}]]}},"settings":{"executionOrder":"v1"},"staticData":null,"meta":{"templateCredsSetupCompleted":true},"pinData":{},"versionId":"421c345f-174c-47ce-8ff3-a0cbdfbdee37","triggerCount":0,"tags":[],"Github_Id":"yanix2445","Gmail":"yanis.amine.harrat@gmail.com","Repo GitHub":"https://github.com/yanix2445/n8n/tree/main","DB Airtable":"https://airtable.com/appMUIQdL0A8aWR0S/tblT7wW1fQXKxMAFn/viwEujUxWO29ErVzH?blocks=hide"}